prollytree-0.3.1.dist-info/METADATA
prollytree-0.3.1.dist-info/WHEEL
prollytree-0.3.1.dist-info/licenses/LICENSE
prollytree/__init__.py
prollytree/prollytree.cpython-311-darwin.so
prollytree/prollytree.pyi
prollytree-0.3.1.dist-info/RECORD
