Metadata-Version: 2.4
Name: prollytree
Version: 0.3.1
Classifier: Development Status :: 4 - Beta
Classifier: Intended Audience :: Developers
Classifier: License :: OSI Approved :: Apache Software License
Classifier: Programming Language :: Python :: 3
Classifier: Programming Language :: Python :: 3.8
Classifier: Programming Language :: Python :: 3.9
Classifier: Programming Language :: Python :: 3.10
Classifier: Programming Language :: Python :: 3.11
Classifier: Programming Language :: Python :: 3.12
Classifier: Programming Language :: Rust
Classifier: Topic :: Software Development :: Libraries :: Python Modules
Classifier: Topic :: Database
Classifier: Topic :: Security :: Cryptography
License-File: LICENSE
Summary: Python bindings for ProllyTree - a probabilistic tree for efficient storage and retrieval
Keywords: prolly,tree,probabilistic,merkle,hash,data-structures,btree,merkle-tree
Author: Feng Zhang <f.feng.zhang@gmail.com>
Author-email: Feng Zhang <f.feng.zhang@gmail.com>
Maintainer-email: Feng Zhang <f.feng.zhang@gmail.com>
License: Apache-2.0
Requires-Python: >=3.8
Project-URL: Homepage, https://github.com/zhangfengcdt/prollytree
Project-URL: Documentation, https://docs.rs/prollytree
Project-URL: Repository, https://github.com/zhangfengcdt/prollytree.git
Project-URL: Bug Tracker, https://github.com/zhangfengcdt/prollytree/issues
